{
   "_name" : "hpb",
   "_typeName" : "ObjectConstruct",
   "_version" : "VER3",
   "animations" : [],
   "finder" : {
      "_typeName" : "FindableGeometryElement",
      "geom" : {
         "_typeName" : "IdenticGeometry"
      }
   },
   "id" : 0,
   "position" : {
      "_typeName" : "PositionElement",
      "angle" : 0,
      "offset" : [ 0, 0 ],
      "scaleX" : 1,
      "scaleY" : 1
   },
   "selector" : {
      "_typeName" : "PressableAndClickableElement",
      "clickTime" : 500
   },
   "skin" : {
      "_typeName" : "CanvasLayout",
      "adjustment" : 0,
      "box" : {
         "_typeName" : "RelativeBox",
         "height" : {
            "_typeName" : "RelativeValue",
            "type" : 0,
            "value" : 0
         },
         "offset" : {
            "_empty" : true
         },
         "width" : {
            "_typeName" : "RelativeValue",
            "type" : 0,
            "value" : 0
         }
      },
      "list" : [
         {
            "_typeName" : "CanvasLayout",
            "adjustment" : 0,
            "box" : {
               "_typeName" : "PixelBox",
               "height" : 2,
               "width" : 100
            },
            "list" : [
               {
                  "_typeName" : "StaticFilledRect",
                  "box" : {
                     "_typeName" : "RelativeBox",
                     "height" : {
                        "_typeName" : "RelativeValue",
                        "type" : 0,
                        "value" : 0
                     },
                     "offset" : {
                        "_empty" : true
                     },
                     "width" : {
                        "_typeName" : "RelativeValue",
                        "type" : 0,
                        "value" : 0
                     }
                  },
                  "color" : [ 1, 0, 0, 1 ],
                  "position" : {
                     "_typeName" : "AligningOffset",
                     "horAlign" : 1,
                     "horOffset" : {
                        "_typeName" : "RelativeValue",
                        "type" : 1,
                        "value" : 0
                     },
                     "vertAlign" : 1,
                     "vertOffset" : {
                        "_typeName" : "RelativeValue",
                        "type" : 1,
                        "value" : 0
                     }
                  }
               },
               {
                  "_name" : "hpb",
                  "_typeName" : "ObjectConstruct",
                  "animations" : [],
                  "finder" : {
                     "_typeName" : "FindableGeometryElement",
                     "geom" : {
                        "_typeName" : "IdenticGeometry"
                     }
                  },
                  "id" : 0,
                  "position" : {
                     "_typeName" : "PositionElement",
                     "angle" : 0,
                     "offset" : [ 0, 0 ],
                     "scaleX" : 1,
                     "scaleY" : 1
                  },
                  "selector" : {
                     "_typeName" : "PressableAndClickableElement",
                     "clickTime" : 500
                  },
                  "skin" : {
                     "_typeName" : "StaticTextureRect",
                     "box" : {
                        "_typeName" : "RelativeBox",
                        "height" : {
                           "_typeName" : "RelativeValue",
                           "type" : 0,
                           "value" : 0
                        },
                        "offset" : {
                           "_empty" : true
                        },
                        "width" : {
                           "_typeName" : "RelativeValue",
                           "type" : 0,
                           "value" : 0
                        }
                     },
                     "color" : [ 0, 1, 0, 1 ],
                     "imageName" : "",
                     "position" : {
                        "_typeName" : "AligningOffset",
                        "horAlign" : 0,
                        "horOffset" : {
                           "_typeName" : "RelativeValue",
                           "type" : 1,
                           "value" : 0
                        },
                        "vertAlign" : 1,
                        "vertOffset" : {
                           "_typeName" : "RelativeValue",
                           "type" : 1,
                           "value" : 0
                        }
                     }
                  },
                  "transitionAnimations" : []
               }
            ],
            "position" : {
               "_typeName" : "AligningOffset",
               "horAlign" : 1,
               "horOffset" : {
                  "_typeName" : "RelativeValue",
                  "type" : 1,
                  "value" : 0
               },
               "vertAlign" : 1,
               "vertOffset" : {
                  "_typeName" : "RelativeValue",
                  "type" : 1,
                  "value" : 0
               }
            }
         },
         {
            "_name" : "Row",
            "_typeName" : "LinearLayout",
            "list" : [
               {
                  "_name" : "bk",
                  "_typeName" : "StaticTextureRect",
                  "box" : {
                     "_typeName" : "PixelBox",
                     "height" : 32,
                     "width" : 32
                  },
                  "color" : [ 1, 1, 1, 1 ],
                  "imageName" : "модули\\bk.png",
                  "position" : {
                     "_typeName" : "AligningOffset",
                     "horAlign" : 0,
                     "horOffset" : {
                        "_typeName" : "RelativeValue",
                        "type" : 1,
                        "value" : 0
                     },
                     "vertAlign" : 1,
                     "vertOffset" : {
                        "_typeName" : "RelativeValue",
                        "type" : 1,
                        "value" : 0
                     }
                  }
               },
               {
                  "_name" : "bus",
                  "_typeName" : "StaticTextureRect",
                  "box" : {
                     "_typeName" : "PixelBox",
                     "height" : 32,
                     "width" : 32
                  },
                  "color" : [ 1, 1, 1, 1 ],
                  "imageName" : "модули\\bus.png",
                  "position" : {
                     "_typeName" : "AligningOffset",
                     "horAlign" : 0,
                     "horOffset" : {
                        "_typeName" : "RelativeValue",
                        "type" : 1,
                        "value" : 5
                     },
                     "vertAlign" : 1,
                     "vertOffset" : {
                        "_typeName" : "RelativeValue",
                        "type" : 1,
                        "value" : 0
                     }
                  }
               },
               {
                  "_name" : "bus2",
                  "_typeName" : "StaticTextureRect",
                  "box" : {
                     "_typeName" : "PixelBox",
                     "height" : 32,
                     "width" : 32
                  },
                  "color" : [ 1, 1, 1, 1 ],
                  "imageName" : "модули\\bus2.png",
                  "position" : {
                     "_typeName" : "AligningOffset",
                     "horAlign" : 0,
                     "horOffset" : {
                        "_typeName" : "RelativeValue",
                        "type" : 1,
                        "value" : 5
                     },
                     "vertAlign" : 1,
                     "vertOffset" : {
                        "_typeName" : "RelativeValue",
                        "type" : 1,
                        "value" : 0
                     }
                  }
               },
               {
                  "_name" : "dvig",
                  "_typeName" : "StaticTextureRect",
                  "box" : {
                     "_typeName" : "PixelBox",
                     "height" : 32,
                     "width" : 32
                  },
                  "color" : [ 1, 1, 1, 1 ],
                  "imageName" : "модули\\dvig.png",
                  "position" : {
                     "_typeName" : "AligningOffset",
                     "horAlign" : 0,
                     "horOffset" : {
                        "_typeName" : "RelativeValue",
                        "type" : 1,
                        "value" : 5
                     },
                     "vertAlign" : 1,
                     "vertOffset" : {
                        "_typeName" : "RelativeValue",
                        "type" : 1,
                        "value" : 0
                     }
                  }
               },
               {
                  "_name" : "dvig2",
                  "_typeName" : "StaticTextureRect",
                  "box" : {
                     "_typeName" : "PixelBox",
                     "height" : 32,
                     "width" : 32
                  },
                  "color" : [ 1, 1, 1, 1 ],
                  "imageName" : "земля\\..\\модули\\dvig2.png",
                  "position" : {
                     "_typeName" : "AligningOffset",
                     "horAlign" : 0,
                     "horOffset" : {
                        "_typeName" : "RelativeValue",
                        "type" : 1,
                        "value" : 5
                     },
                     "vertAlign" : 1,
                     "vertOffset" : {
                        "_typeName" : "RelativeValue",
                        "type" : 1,
                        "value" : 0
                     }
                  }
               },
               {
                  "_name" : "gus",
                  "_typeName" : "StaticTextureRect",
                  "box" : {
                     "_typeName" : "PixelBox",
                     "height" : 32,
                     "width" : 32
                  },
                  "color" : [ 1, 1, 1, 1 ],
                  "imageName" : "модули\\gus.png",
                  "position" : {
                     "_typeName" : "AligningOffset",
                     "horAlign" : 0,
                     "horOffset" : {
                        "_typeName" : "RelativeValue",
                        "type" : 1,
                        "value" : 5
                     },
                     "vertAlign" : 1,
                     "vertOffset" : {
                        "_typeName" : "RelativeValue",
                        "type" : 1,
                        "value" : 0
                     }
                  }
               },
               {
                  "_name" : "gus2",
                  "_typeName" : "StaticTextureRect",
                  "box" : {
                     "_typeName" : "PixelBox",
                     "height" : 32,
                     "width" : 32
                  },
                  "color" : [ 1, 1, 1, 1 ],
                  "imageName" : "модули\\gus2.png",
                  "position" : {
                     "_typeName" : "AligningOffset",
                     "horAlign" : 0,
                     "horOffset" : {
                        "_typeName" : "RelativeValue",
                        "type" : 1,
                        "value" : 5
                     },
                     "vertAlign" : 1,
                     "vertOffset" : {
                        "_typeName" : "RelativeValue",
                        "type" : 1,
                        "value" : 0
                     }
                  }
               },
               {
                  "_name" : "ggun",
                  "_typeName" : "StaticTextureRect",
                  "box" : {
                     "_typeName" : "PixelBox",
                     "height" : 32,
                     "width" : 32
                  },
                  "color" : [ 1, 1, 1, 1 ],
                  "imageName" : "модули\\ggun.png",
                  "position" : {
                     "_typeName" : "AligningOffset",
                     "horAlign" : 0,
                     "horOffset" : {
                        "_typeName" : "RelativeValue",
                        "type" : 1,
                        "value" : 5
                     },
                     "vertAlign" : 1,
                     "vertOffset" : {
                        "_typeName" : "RelativeValue",
                        "type" : 1,
                        "value" : 0
                     }
                  }
               },
               {
                  "_name" : "ggun2",
                  "_typeName" : "StaticTextureRect",
                  "box" : {
                     "_typeName" : "PixelBox",
                     "height" : 32,
                     "width" : 32
                  },
                  "color" : [ 1, 1, 1, 1 ],
                  "imageName" : "модули\\ggun2.png",
                  "position" : {
                     "_typeName" : "AligningOffset",
                     "horAlign" : 0,
                     "horOffset" : {
                        "_typeName" : "RelativeValue",
                        "type" : 1,
                        "value" : 5
                     },
                     "vertAlign" : 1,
                     "vertOffset" : {
                        "_typeName" : "RelativeValue",
                        "type" : 1,
                        "value" : 0
                     }
                  }
               },
               {
                  "_name" : "rad",
                  "_typeName" : "StaticTextureRect",
                  "box" : {
                     "_typeName" : "PixelBox",
                     "height" : 32,
                     "width" : 32
                  },
                  "color" : [ 1, 1, 1, 1 ],
                  "imageName" : "модули\\rad.png",
                  "position" : {
                     "_typeName" : "AligningOffset",
                     "horAlign" : 0,
                     "horOffset" : {
                        "_typeName" : "RelativeValue",
                        "type" : 1,
                        "value" : 5
                     },
                     "vertAlign" : 1,
                     "vertOffset" : {
                        "_typeName" : "RelativeValue",
                        "type" : 1,
                        "value" : 0
                     }
                  }
               },
               {
                  "_name" : "rad2",
                  "_typeName" : "StaticTextureRect",
                  "box" : {
                     "_typeName" : "PixelBox",
                     "height" : 32,
                     "width" : 32
                  },
                  "color" : [ 1, 1, 1, 1 ],
                  "imageName" : "модули\\rad2.png",
                  "position" : {
                     "_typeName" : "AligningOffset",
                     "horAlign" : 0,
                     "horOffset" : {
                        "_typeName" : "RelativeValue",
                        "type" : 1,
                        "value" : 5
                     },
                     "vertAlign" : 1,
                     "vertOffset" : {
                        "_typeName" : "RelativeValue",
                        "type" : 1,
                        "value" : 0
                     }
                  }
               },
               {
                  "_name" : "trip",
                  "_typeName" : "StaticTextureRect",
                  "box" : {
                     "_typeName" : "PixelBox",
                     "height" : 32,
                     "width" : 32
                  },
                  "color" : [ 1, 1, 1, 1 ],
                  "imageName" : "модули\\trip.png",
                  "position" : {
                     "_typeName" : "AligningOffset",
                     "horAlign" : 0,
                     "horOffset" : {
                        "_typeName" : "RelativeValue",
                        "type" : 1,
                        "value" : 5
                     },
                     "vertAlign" : 1,
                     "vertOffset" : {
                        "_typeName" : "RelativeValue",
                        "type" : 1,
                        "value" : 0
                     }
                  }
               },
               {
                  "_name" : "trip2",
                  "_typeName" : "StaticTextureRect",
                  "box" : {
                     "_typeName" : "PixelBox",
                     "height" : 32,
                     "width" : 32
                  },
                  "color" : [ 1, 1, 1, 1 ],
                  "imageName" : "модули\\trip2.png",
                  "position" : {
                     "_typeName" : "AligningOffset",
                     "horAlign" : 0,
                     "horOffset" : {
                        "_typeName" : "RelativeValue",
                        "type" : 1,
                        "value" : 5
                     },
                     "vertAlign" : 1,
                     "vertOffset" : {
                        "_typeName" : "RelativeValue",
                        "type" : 1,
                        "value" : 0
                     }
                  }
               }
            ],
            "position" : {
               "_typeName" : "AligningOffset",
               "horAlign" : 1,
               "horOffset" : {
                  "_typeName" : "RelativeValue",
                  "type" : 1,
                  "value" : 0
               },
               "vertAlign" : 1,
               "vertOffset" : {
                  "_typeName" : "RelativeValue",
                  "type" : 1,
                  "value" : 15
               }
            },
            "skin" : {
               "_typeName" : "HorizontalLayoutSkin",
               "adjustment" : 1,
               "align" : 1,
               "box" : {
                  "_typeName" : "RelativeBox",
                  "height" : {
                     "_typeName" : "RelativeValue",
                     "type" : 0,
                     "value" : 0
                  },
                  "offset" : {
                     "_empty" : true
                  },
                  "width" : {
                     "_typeName" : "RelativeValue",
                     "type" : 0,
                     "value" : 0
                  }
               },
               "padding" : {
                  "_typeName" : "RelativeValue",
                  "type" : 1,
                  "value" : 5
               }
            },
            "skipInvisibleElements" : true
         },
         {
            "_name" : "Row2",
            "_typeName" : "LinearLayout",
            "list" : [
               {
                  "_name" : "rldr2",
                  "_typeName" : "StaticTextureRect",
                  "box" : {
                     "_typeName" : "PixelBox",
                     "height" : 32,
                     "width" : 32
                  },
                  "color" : [ 1, 1, 1, 1 ],
                  "imageName" : "экипаж\\rloder2.png",
                  "position" : {
                     "_typeName" : "AligningOffset",
                     "horAlign" : 0,
                     "horOffset" : {
                        "_typeName" : "RelativeValue",
                        "type" : 1,
                        "value" : 0
                     },
                     "vertAlign" : 1,
                     "vertOffset" : {
                        "_typeName" : "RelativeValue",
                        "type" : 1,
                        "value" : 0
                     }
                  }
               },
               {
                  "_name" : "rldr",
                  "_typeName" : "StaticTextureRect",
                  "box" : {
                     "_typeName" : "PixelBox",
                     "height" : 32,
                     "width" : 32
                  },
                  "color" : [ 1, 1, 1, 1 ],
                  "imageName" : "экипаж\\rloder.png",
                  "position" : {
                     "_typeName" : "AligningOffset",
                     "horAlign" : 0,
                     "horOffset" : {
                        "_typeName" : "RelativeValue",
                        "type" : 1,
                        "value" : 5
                     },
                     "vertAlign" : 1,
                     "vertOffset" : {
                        "_typeName" : "RelativeValue",
                        "type" : 1,
                        "value" : 0
                     }
                  }
               },
               {
                  "_name" : "egnr2",
                  "_typeName" : "StaticTextureRect",
                  "box" : {
                     "_typeName" : "PixelBox",
                     "height" : 32,
                     "width" : 32
                  },
                  "color" : [ 1, 1, 1, 1 ],
                  "imageName" : "экипаж\\engener2.png",
                  "position" : {
                     "_typeName" : "AligningOffset",
                     "horAlign" : 0,
                     "horOffset" : {
                        "_typeName" : "RelativeValue",
                        "type" : 1,
                        "value" : 5
                     },
                     "vertAlign" : 1,
                     "vertOffset" : {
                        "_typeName" : "RelativeValue",
                        "type" : 1,
                        "value" : 0
                     }
                  }
               },
               {
                  "_name" : "egnr",
                  "_typeName" : "StaticTextureRect",
                  "box" : {
                     "_typeName" : "PixelBox",
                     "height" : 32,
                     "width" : 32
                  },
                  "color" : [ 1, 1, 1, 1 ],
                  "imageName" : "экипаж\\engener.png",
                  "position" : {
                     "_typeName" : "AligningOffset",
                     "horAlign" : 0,
                     "horOffset" : {
                        "_typeName" : "RelativeValue",
                        "type" : 1,
                        "value" : 5
                     },
                     "vertAlign" : 1,
                     "vertOffset" : {
                        "_typeName" : "RelativeValue",
                        "type" : 1,
                        "value" : 0
                     }
                  }
               },
               {
                  "_name" : "gner2",
                  "_typeName" : "StaticTextureRect",
                  "box" : {
                     "_typeName" : "PixelBox",
                     "height" : 32,
                     "width" : 32
                  },
                  "color" : [ 1, 1, 1, 1 ],
                  "imageName" : "экипаж\\gunner2.png",
                  "position" : {
                     "_typeName" : "AligningOffset",
                     "horAlign" : 0,
                     "horOffset" : {
                        "_typeName" : "RelativeValue",
                        "type" : 1,
                        "value" : 5
                     },
                     "vertAlign" : 1,
                     "vertOffset" : {
                        "_typeName" : "RelativeValue",
                        "type" : 1,
                        "value" : 0
                     }
                  }
               },
               {
                  "_name" : "gner",
                  "_typeName" : "StaticTextureRect",
                  "box" : {
                     "_typeName" : "PixelBox",
                     "height" : 32,
                     "width" : 32
                  },
                  "color" : [ 1, 1, 1, 1 ],
                  "imageName" : "экипаж\\gunner.png",
                  "position" : {
                     "_typeName" : "AligningOffset",
                     "horAlign" : 0,
                     "horOffset" : {
                        "_typeName" : "RelativeValue",
                        "type" : 1,
                        "value" : 5
                     },
                     "vertAlign" : 1,
                     "vertOffset" : {
                        "_typeName" : "RelativeValue",
                        "type" : 1,
                        "value" : 0
                     }
                  }
               },
               {
                  "_name" : "drv2",
                  "_typeName" : "StaticTextureRect",
                  "box" : {
                     "_typeName" : "PixelBox",
                     "height" : 32,
                     "width" : 32
                  },
                  "color" : [ 1, 1, 1, 1 ],
                  "imageName" : "экипаж\\driver2.png",
                  "position" : {
                     "_typeName" : "AligningOffset",
                     "horAlign" : 0,
                     "horOffset" : {
                        "_typeName" : "RelativeValue",
                        "type" : 1,
                        "value" : 5
                     },
                     "vertAlign" : 1,
                     "vertOffset" : {
                        "_typeName" : "RelativeValue",
                        "type" : 1,
                        "value" : 0
                     }
                  }
               },
               {
                  "_name" : "drv",
                  "_typeName" : "StaticTextureRect",
                  "box" : {
                     "_typeName" : "PixelBox",
                     "height" : 32,
                     "width" : 32
                  },
                  "color" : [ 1, 1, 1, 1 ],
                  "imageName" : "экипаж\\driver.png",
                  "position" : {
                     "_typeName" : "AligningOffset",
                     "horAlign" : 0,
                     "horOffset" : {
                        "_typeName" : "RelativeValue",
                        "type" : 1,
                        "value" : 5
                     },
                     "vertAlign" : 1,
                     "vertOffset" : {
                        "_typeName" : "RelativeValue",
                        "type" : 1,
                        "value" : 0
                     }
                  }
               },
               {
                  "_name" : "com",
                  "_typeName" : "StaticTextureRect",
                  "box" : {
                     "_typeName" : "PixelBox",
                     "height" : 32,
                     "width" : 32
                  },
                  "color" : [ 1, 1, 1, 1 ],
                  "imageName" : "экипаж\\comander.png",
                  "position" : {
                     "_typeName" : "AligningOffset",
                     "horAlign" : 0,
                     "horOffset" : {
                        "_typeName" : "RelativeValue",
                        "type" : 1,
                        "value" : 5
                     },
                     "vertAlign" : 1,
                     "vertOffset" : {
                        "_typeName" : "RelativeValue",
                        "type" : 1,
                        "value" : 0
                     }
                  }
               },
               {
                  "_name" : "com2",
                  "_typeName" : "StaticTextureRect",
                  "box" : {
                     "_typeName" : "PixelBox",
                     "height" : 32,
                     "width" : 32
                  },
                  "color" : [ 1, 1, 1, 1 ],
                  "imageName" : "экипаж\\comander2.png",
                  "position" : {
                     "_typeName" : "AligningOffset",
                     "horAlign" : 0,
                     "horOffset" : {
                        "_typeName" : "RelativeValue",
                        "type" : 1,
                        "value" : 5
                     },
                     "vertAlign" : 1,
                     "vertOffset" : {
                        "_typeName" : "RelativeValue",
                        "type" : 1,
                        "value" : 0
                     }
                  }
               },
               {
                  "_name" : "rad",
                  "_typeName" : "StaticTextureRect",
                  "box" : {
                     "_typeName" : "PixelBox",
                     "height" : 32,
                     "width" : 32
                  },
                  "color" : [ 1, 1, 1, 1 ],
                  "imageName" : "экипаж\\radoper.png",
                  "position" : {
                     "_typeName" : "AligningOffset",
                     "horAlign" : 0,
                     "horOffset" : {
                        "_typeName" : "RelativeValue",
                        "type" : 1,
                        "value" : 5
                     },
                     "vertAlign" : 1,
                     "vertOffset" : {
                        "_typeName" : "RelativeValue",
                        "type" : 1,
                        "value" : 0
                     }
                  }
               },
               {
                  "_name" : "rad2",
                  "_typeName" : "StaticTextureRect",
                  "box" : {
                     "_typeName" : "PixelBox",
                     "height" : 32,
                     "width" : 32
                  },
                  "color" : [ 1, 1, 1, 1 ],
                  "imageName" : "экипаж\\radoper2.png",
                  "position" : {
                     "_typeName" : "AligningOffset",
                     "horAlign" : 0,
                     "horOffset" : {
                        "_typeName" : "RelativeValue",
                        "type" : 1,
                        "value" : 5
                     },
                     "vertAlign" : 1,
                     "vertOffset" : {
                        "_typeName" : "RelativeValue",
                        "type" : 1,
                        "value" : 0
                     }
                  }
               }
            ],
            "position" : {
               "_typeName" : "AligningOffset",
               "horAlign" : 1,
               "horOffset" : {
                  "_typeName" : "RelativeValue",
                  "type" : 1,
                  "value" : 0
               },
               "vertAlign" : 1,
               "vertOffset" : {
                  "_typeName" : "RelativeValue",
                  "type" : 1,
                  "value" : 50
               }
            },
            "skin" : {
               "_typeName" : "HorizontalLayoutSkin",
               "adjustment" : 1,
               "align" : 1,
               "box" : {
                  "_typeName" : "RelativeBox",
                  "height" : {
                     "_typeName" : "RelativeValue",
                     "type" : 0,
                     "value" : 0
                  },
                  "offset" : {
                     "_empty" : true
                  },
                  "width" : {
                     "_typeName" : "RelativeValue",
                     "type" : 0,
                     "value" : 0
                  }
               },
               "padding" : {
                  "_typeName" : "RelativeValue",
                  "type" : 1,
                  "value" : 5
               }
            },
            "skipInvisibleElements" : false
         }
      ],
      "position" : {
         "_typeName" : "AligningOffset",
         "horAlign" : 1,
         "horOffset" : {
            "_typeName" : "RelativeValue",
            "type" : 1,
            "value" : 0
         },
         "vertAlign" : 1,
         "vertOffset" : {
            "_typeName" : "RelativeValue",
            "type" : 1,
            "value" : 0
         }
      }
   },
   "transitionAnimations" : []
}
